python_log_sanitizer/__init__.py
test/__init__.py
test/test_sanitizer_filter.py
python_log_sanitizer-0.0.3.dist-info/LICENSE
python_log_sanitizer-0.0.3.dist-info/METADATA
python_log_sanitizer-0.0.3.dist-info/WHEEL
python_log_sanitizer-0.0.3.dist-info/top_level.txt
python_log_sanitizer-0.0.3.dist-info/RECORD
