Metadata-Version: 2.1
Name: python-log-sanitizer
Version: 0.0.3
Summary: Log Sanitizer
Home-page: http://github.com/rai200890/python_log_sanitizer
Author: Raissa Ferreira
Author-email: rai200890@gmail.com
License: MIT
Platform: UNKNOWN
Classifier: Environment :: Web Environment
Classifier: Intended Audience :: Developers
Classifier: License :: OSI Approved :: MIT License
Classifier: Natural Language :: English
Classifier: Operating System :: OS Independent
Classifier: Programming Language :: Python :: 3 :: Only
Classifier: Topic :: System :: Logging
Requires-Python: >=3.4.*
